platformer/__init__.py
platformer/game.py
Python_Platformer_Fin-0.1.dist-info/LICENSE.txt
Python_Platformer_Fin-0.1.dist-info/METADATA
Python_Platformer_Fin-0.1.dist-info/WHEEL
Python_Platformer_Fin-0.1.dist-info/entry_points.txt
Python_Platformer_Fin-0.1.dist-info/top_level.txt
Python_Platformer_Fin-0.1.dist-info/RECORD
