Metadata-Version: 2.1
Name: Python-Platformer-Fin
Version: 0.1
Summary: A simple pygame platformer
Author: Yogiram
Author-email: yogiramkv@gmail.com
Classifier: Programming Language :: Python :: 3
Classifier: License :: OSI Approved :: MIT License
Classifier: Operating System :: OS Independent
Requires-Python: >=3.6
License-File: LICENSE.txt
Requires-Dist: pygame ==2.5.2
